{
  "project_info": {
    "project_number": "683789674005",
    "project_id": "wallet-app-8f048",
    "storage_bucket": "wallet-app-8f048.appspot.com"
  },
  "client": [
    {
      "client_info": {
        "mobilesdk_app_id": "1:683789674005:android:7a4c8db03f702876dfd01c",
        "android_client_info": {
          "package_name": "com.example.interview_wallet_app"
        }
      },
      "oauth_client": [],
      "api_key": [
        {
          "current_key": "AIzaSyA7-jGoAE8P6iKtivW5ONKF7PUa52EoMRg"
        }
      ],
      "services": {
        "appinvite_service": {
          "other_platform_oauth_client": []
        }
      }
    }
  ],
  "configuration_version": "1"
}